{
  "file": "1988693a-a0bb-4906-9c54-ea177246d40d.html",
  "medications": [
    {
      "rx_cui": "20352",
      "normalized_name": "carvedilol",
      "cui_type": "IN",
      "mapping_method": "generic_name",
      "mapping_confidence": 1.0,
      "flag": null,
      "text": "carvedilol",
      "confidence": 0.98,
      "active_status": "active",
      "start_offset": 26169,
      "end_offset": 26179
    },
    {
      "rx_cui": "1545653",
      "normalized_name": "empagliflozin",
      "cui_type": "IN",
      "mapping_method": "generic_name",
      "mapping_confidence": 1.0,
      "flag": null,
      "text": "empagliflozin",
      "confidence": 0.98,
      "active_status": "active",
      "start_offset": 26277,
      "end_offset": 26290
    },
    {
      "rx_cui": "42375",
      "normalized_name": "leuprolide",
      "cui_type": "IN",
      "mapping_method": "generic_name",
      "mapping_confidence": 1.0,
      "flag": null,
      "text": "leuprolide",
      "confidence": 0.98,
      "active_status": "active",
      "start_offset": 26367,
      "end_offset": 26377
    },
    {
      "rx_cui": "20352",
      "normalized_name": "carvedilol",
      "cui_type": "IN",
      "mapping_method": "brand_name",
      "mapping_confidence": 0.96,
      "flag": null,
      "text": "COREG",
      "confidence": 0.96,
      "active_status": "active",
      "start_offset": 26181,
      "end_offset": 26186
    },
    {
      "rx_cui": "1545653",
      "normalized_name": "empagliflozin",
      "cui_type": "IN",
      "mapping_method": "brand_name",
      "mapping_confidence": 0.96,
      "flag": null,
      "text": "JARDIANCE",
      "confidence": 0.96,
      "active_status": "active",
      "start_offset": 26292,
      "end_offset": 26301
    },
    {
      "rx_cui": "42375",
      "normalized_name": "leuprolide",
      "cui_type": "IN",
      "mapping_method": "brand_name",
      "mapping_confidence": 0.96,
      "flag": null,
      "text": "Lupron",
      "confidence": 0.96,
      "active_status": "active",
      "start_offset": 18465,
      "end_offset": 18471
    },
    {
      "rx_cui": "42375",
      "normalized_name": "leuprolide",
      "cui_type": "IN",
      "mapping_method": "brand_name",
      "mapping_confidence": 0.96,
      "flag": null,
      "text": "lupron",
      "confidence": 0.96,
      "active_status": "active",
      "start_offset": 18518,
      "end_offset": 18524
    },
    {
      "rx_cui": "42375",
      "normalized_name": "leuprolide",
      "cui_type": "IN",
      "mapping_method": "brand_name",
      "mapping_confidence": 0.96,
      "flag": null,
      "text": "Lupron",
      "confidence": 0.96,
      "active_status": "non-active",
      "start_offset": 19836,
      "end_offset": 19842
    },
    {
      "rx_cui": "42375",
      "normalized_name": "leuprolide",
      "cui_type": "IN",
      "mapping_method": "brand_name",
      "mapping_confidence": 0.96,
      "flag": null,
      "text": "lupron",
      "confidence": 0.96,
      "active_status": "active",
      "start_offset": 23296,
      "end_offset": 23302
    },
    {
      "rx_cui": "42375",
      "normalized_name": "leuprolide",
      "cui_type": "IN",
      "mapping_method": "brand_name",
      "mapping_confidence": 0.96,
      "flag": null,
      "text": "LUPRON",
      "confidence": 0.96,
      "active_status": "active",
      "start_offset": 26389,
      "end_offset": 26395
    },
    {
      "rx_cui": "42375",
      "normalized_name": "leuprolide",
      "cui_type": "IN",
      "mapping_method": "brand_name",
      "mapping_confidence": 0.96,
      "flag": null,
      "text": "Lupron",
      "confidence": 0.96,
      "active_status": "active",
      "start_offset": 30097,
      "end_offset": 30103
    },
    {
      "rx_cui": "1656339",
      "normalized_name": "sacubitril / valsartan",
      "cui_type": "MIN",
      "mapping_method": "brand_name",
      "mapping_confidence": 0.96,
      "flag": null,
      "text": "ENTRESTO",
      "confidence": 0.96,
      "active_status": "non-active",
      "start_offset": 27082,
      "end_offset": 27090
    }
  ]
}