{
  "file": "aa601ec4-905c-4531-ac9f-41f260897eec.html",
  "medications": [
    {
      "rx_cui": "1202",
      "normalized_name": "atenolol",
      "cui_type": "IN",
      "mapping_method": "generic_name",
      "mapping_confidence": 1.0,
      "flag": null,
      "text": "Atenolol",
      "confidence": 0.98,
      "active_status": "active",
      "start_offset": 8830,
      "end_offset": 8838
    },
    {
      "rx_cui": "1202",
      "normalized_name": "atenolol",
      "cui_type": "IN",
      "mapping_method": "generic_name",
      "mapping_confidence": 1.0,
      "flag": null,
      "text": "Atenolol",
      "confidence": 0.98,
      "active_status": "active",
      "start_offset": 17034,
      "end_offset": 17042
    },
    {
      "rx_cui": "1202",
      "normalized_name": "atenolol",
      "cui_type": "IN",
      "mapping_method": "generic_name",
      "mapping_confidence": 1.0,
      "flag": null,
      "text": "Atenolol",
      "confidence": 0.98,
      "active_status": "active",
      "start_offset": 21333,
      "end_offset": 21341
    },
    {
      "rx_cui": "1202",
      "normalized_name": "atenolol",
      "cui_type": "IN",
      "mapping_method": "generic_name",
      "mapping_confidence": 1.0,
      "flag": null,
      "text": "Atenolol",
      "confidence": 0.98,
      "active_status": "active",
      "start_offset": 28971,
      "end_offset": 28979
    },
    {
      "rx_cui": "1202",
      "normalized_name": "atenolol",
      "cui_type": "IN",
      "mapping_method": "generic_name",
      "mapping_confidence": 1.0,
      "flag": null,
      "text": "Atenolol",
      "confidence": 0.98,
      "active_status": "active",
      "start_offset": 29775,
      "end_offset": 29783
    },
    {
      "rx_cui": "1202",
      "normalized_name": "atenolol",
      "cui_type": "IN",
      "mapping_method": "generic_name",
      "mapping_confidence": 1.0,
      "flag": null,
      "text": "Atenolol",
      "confidence": 0.98,
      "active_status": "active",
      "start_offset": 47065,
      "end_offset": 47073
    },
    {
      "rx_cui": "1202",
      "normalized_name": "atenolol",
      "cui_type": "IN",
      "mapping_method": "generic_name",
      "mapping_confidence": 1.0,
      "flag": null,
      "text": "Atenolol",
      "confidence": 0.98,
      "active_status": "active",
      "start_offset": 51891,
      "end_offset": 51899
    }
  ]
}