{
  "file": "c1a334ee-04c4-483b-9c79-9dd6f300f948.html",
  "medications": [
    {
      "rx_cui": "6918",
      "normalized_name": "metoprolol",
      "cui_type": "IN",
      "mapping_method": "generic_name",
      "mapping_confidence": 1.0,
      "flag": null,
      "text": "metoprolol",
      "confidence": 0.98,
      "active_status": "active",
      "start_offset": 21200,
      "end_offset": 21210
    },
    {
      "rx_cui": "6918",
      "normalized_name": "metoprolol",
      "cui_type": "IN",
      "mapping_method": "brand_name",
      "mapping_confidence": 0.96,
      "flag": null,
      "text": "TOPROL-XL",
      "confidence": 0.96,
      "active_status": "active",
      "start_offset": 21222,
      "end_offset": 21231
    },
    {
      "rx_cui": "9947",
      "normalized_name": "sotalol",
      "cui_type": "IN",
      "mapping_method": "brand_name",
      "mapping_confidence": 0.96,
      "flag": null,
      "text": "sorine",
      "confidence": 0.96,
      "active_status": "active",
      "start_offset": 19430,
      "end_offset": 19436
    }
  ]
}