{
  "file": "1a94f09e-a0a0-4bf7-a876-26c3eddd7d18_clean.html",
  "medications": [
    {
      "rx_cui": "1364430",
      "normalized_name": "apixaban",
      "cui_type": "IN",
      "mapping_method": "generic_name",
      "mapping_confidence": 1.0,
      "flag": null,
      "text": "apixaban",
      "confidence": 0.98,
      "active_status": "non-active",
      "start_offset": 21843,
      "end_offset": 21851
    },
    {
      "rx_cui": "1364430",
      "normalized_name": "apixaban",
      "cui_type": "IN",
      "mapping_method": "generic_name",
      "mapping_confidence": 1.0,
      "flag": null,
      "text": "apixaban",
      "confidence": 0.98,
      "active_status": "non-active",
      "start_offset": 34444,
      "end_offset": 34452
    },
    {
      "rx_cui": "6918",
      "normalized_name": "metoprolol",
      "cui_type": "IN",
      "mapping_method": "generic_name",
      "mapping_confidence": 1.0,
      "flag": null,
      "text": "Metoprolol",
      "confidence": 0.98,
      "active_status": "active",
      "start_offset": 2774,
      "end_offset": 2784
    },
    {
      "rx_cui": "6918",
      "normalized_name": "metoprolol",
      "cui_type": "IN",
      "mapping_method": "generic_name",
      "mapping_confidence": 1.0,
      "flag": null,
      "text": "Metoprolol",
      "confidence": 0.98,
      "active_status": "active",
      "start_offset": 26414,
      "end_offset": 26424
    },
    {
      "rx_cui": "6918",
      "normalized_name": "metoprolol",
      "cui_type": "IN",
      "mapping_method": "generic_name",
      "mapping_confidence": 1.0,
      "flag": null,
      "text": "Metoprolol",
      "confidence": 0.98,
      "active_status": "active",
      "start_offset": 26835,
      "end_offset": 26845
    }
  ]
}